throttlex/__init__.py
throttlex-1.0.0.dist-info/LICENSE
throttlex-1.0.0.dist-info/METADATA
throttlex-1.0.0.dist-info/WHEEL
throttlex-1.0.0.dist-info/top_level.txt
throttlex-1.0.0.dist-info/RECORD
